boxing/__init__.py
boxing/boxes.json
boxing/boxing.py
boxing-0.1.4.dist-info/DESCRIPTION.rst
boxing-0.1.4.dist-info/METADATA
boxing-0.1.4.dist-info/RECORD
boxing-0.1.4.dist-info/WHEEL
boxing-0.1.4.dist-info/metadata.json
boxing-0.1.4.dist-info/top_level.txt
