Metadata-Version: 2.0
Name: boxing
Version: 0.1.4
Summary: Draw boxes like never before!
Home-page: https://github.com/acifani/boxing
Author: Alessandro Cifani
Author-email: alessandro.cifani@gmail.com
License: BSD
Platform: UNKNOWN
Classifier: Development Status :: 3 - Alpha
Classifier: Intended Audience :: Developers
Classifier: License :: OSI Approved :: BSD License
Classifier: Operating System :: OS Independent
Classifier: Topic :: Software Development :: Libraries :: Python Modules
Classifier: Programming Language :: Python
